my_minipack/__init__.py
my_minipack/logger.py
my_minipack/progress.py
my_minipack-1.0.1.dist-info/LICENSE.md
my_minipack-1.0.1.dist-info/METADATA
my_minipack-1.0.1.dist-info/WHEEL
my_minipack-1.0.1.dist-info/top_level.txt
my_minipack-1.0.1.dist-info/RECORD
